{
  "type": "GROUP",
"name": "All Requests",
"path": "",
"pathFormatted": "group_missing-name--1146707516",
"stats": {
    "name": "All Requests",
    "numberOfRequests": {
        "total": 15,
        "ok": 15,
        "ko": 0
    },
    "minResponseTime": {
        "total": 16,
        "ok": 16,
        "ko": 0
    },
    "maxResponseTime": {
        "total": 759,
        "ok": 759,
        "ko": 0
    },
    "meanResponseTime": {
        "total": 280,
        "ok": 280,
        "ko": 0
    },
    "standardDeviation": {
        "total": 306,
        "ok": 306,
        "ko": 0
    },
    "percentiles1": {
        "total": 50,
        "ok": 50,
        "ko": 0
    },
    "percentiles2": {
        "total": 602,
        "ok": 602,
        "ko": 0
    },
    "percentiles3": {
        "total": 745,
        "ok": 745,
        "ko": 0
    },
    "percentiles4": {
        "total": 756,
        "ok": 756,
        "ko": 0
    },
    "group1": {
    "name": "t < 800 ms",
    "htmlName": "t < 800 ms",
    "count": 15,
    "percentage": 100
},
    "group2": {
    "name": "800 ms <= t < 1200 ms",
    "htmlName": "t >= 800 ms <br> t < 1200 ms",
    "count": 0,
    "percentage": 0
},
    "group3": {
    "name": "t >= 1200 ms",
    "htmlName": "t >= 1200 ms",
    "count": 0,
    "percentage": 0
},
    "group4": {
    "name": "failed",
    "htmlName": "failed",
    "count": 0,
    "percentage": 0
},
    "meanNumberOfRequestsPerSecond": {
        "total": 0.8823529411764706,
        "ok": 0.8823529411764706,
        "ko": 0
    }
},
"contents": {
"req_register-reques--107368910": {
        "type": "REQUEST",
        "name": "Register request",
"path": "Register request",
"pathFormatted": "req_register-reques--107368910",
"stats": {
    "name": "Register request",
    "numberOfRequests": {
        "total": 3,
        "ok": 3,
        "ko": 0
    },
    "minResponseTime": {
        "total": 538,
        "ok": 538,
        "ko": 0
    },
    "maxResponseTime": {
        "total": 606,
        "ok": 606,
        "ko": 0
    },
    "meanResponseTime": {
        "total": 581,
        "ok": 581,
        "ko": 0
    },
    "standardDeviation": {
        "total": 30,
        "ok": 30,
        "ko": 0
    },
    "percentiles1": {
        "total": 598,
        "ok": 598,
        "ko": 0
    },
    "percentiles2": {
        "total": 602,
        "ok": 602,
        "ko": 0
    },
    "percentiles3": {
        "total": 605,
        "ok": 605,
        "ko": 0
    },
    "percentiles4": {
        "total": 606,
        "ok": 606,
        "ko": 0
    },
    "group1": {
    "name": "t < 800 ms",
    "htmlName": "t < 800 ms",
    "count": 3,
    "percentage": 100
},
    "group2": {
    "name": "800 ms <= t < 1200 ms",
    "htmlName": "t >= 800 ms <br> t < 1200 ms",
    "count": 0,
    "percentage": 0
},
    "group3": {
    "name": "t >= 1200 ms",
    "htmlName": "t >= 1200 ms",
    "count": 0,
    "percentage": 0
},
    "group4": {
    "name": "failed",
    "htmlName": "failed",
    "count": 0,
    "percentage": 0
},
    "meanNumberOfRequestsPerSecond": {
        "total": 0.17647058823529413,
        "ok": 0.17647058823529413,
        "ko": 0
    }
}
    },"req_login-request-837563576": {
        "type": "REQUEST",
        "name": "Login request",
"path": "Login request",
"pathFormatted": "req_login-request-837563576",
"stats": {
    "name": "Login request",
    "numberOfRequests": {
        "total": 3,
        "ok": 3,
        "ko": 0
    },
    "minResponseTime": {
        "total": 659,
        "ok": 659,
        "ko": 0
    },
    "maxResponseTime": {
        "total": 759,
        "ok": 759,
        "ko": 0
    },
    "meanResponseTime": {
        "total": 719,
        "ok": 719,
        "ko": 0
    },
    "standardDeviation": {
        "total": 43,
        "ok": 43,
        "ko": 0
    },
    "percentiles1": {
        "total": 739,
        "ok": 739,
        "ko": 0
    },
    "percentiles2": {
        "total": 749,
        "ok": 749,
        "ko": 0
    },
    "percentiles3": {
        "total": 757,
        "ok": 757,
        "ko": 0
    },
    "percentiles4": {
        "total": 759,
        "ok": 759,
        "ko": 0
    },
    "group1": {
    "name": "t < 800 ms",
    "htmlName": "t < 800 ms",
    "count": 3,
    "percentage": 100
},
    "group2": {
    "name": "800 ms <= t < 1200 ms",
    "htmlName": "t >= 800 ms <br> t < 1200 ms",
    "count": 0,
    "percentage": 0
},
    "group3": {
    "name": "t >= 1200 ms",
    "htmlName": "t >= 1200 ms",
    "count": 0,
    "percentage": 0
},
    "group4": {
    "name": "failed",
    "htmlName": "failed",
    "count": 0,
    "percentage": 0
},
    "meanNumberOfRequestsPerSecond": {
        "total": 0.17647058823529413,
        "ok": 0.17647058823529413,
        "ko": 0
    }
}
    },"req_get-all-users-r-1488424398": {
        "type": "REQUEST",
        "name": "Get all users request",
"path": "Get all users request",
"pathFormatted": "req_get-all-users-r-1488424398",
"stats": {
    "name": "Get all users request",
    "numberOfRequests": {
        "total": 7,
        "ok": 7,
        "ko": 0
    },
    "minResponseTime": {
        "total": 16,
        "ok": 16,
        "ko": 0
    },
    "maxResponseTime": {
        "total": 58,
        "ok": 58,
        "ko": 0
    },
    "meanResponseTime": {
        "total": 29,
        "ok": 29,
        "ko": 0
    },
    "standardDeviation": {
        "total": 13,
        "ok": 13,
        "ko": 0
    },
    "percentiles1": {
        "total": 27,
        "ok": 27,
        "ko": 0
    },
    "percentiles2": {
        "total": 28,
        "ok": 28,
        "ko": 0
    },
    "percentiles3": {
        "total": 49,
        "ok": 49,
        "ko": 0
    },
    "percentiles4": {
        "total": 56,
        "ok": 56,
        "ko": 0
    },
    "group1": {
    "name": "t < 800 ms",
    "htmlName": "t < 800 ms",
    "count": 7,
    "percentage": 100
},
    "group2": {
    "name": "800 ms <= t < 1200 ms",
    "htmlName": "t >= 800 ms <br> t < 1200 ms",
    "count": 0,
    "percentage": 0
},
    "group3": {
    "name": "t >= 1200 ms",
    "htmlName": "t >= 1200 ms",
    "count": 0,
    "percentage": 0
},
    "group4": {
    "name": "failed",
    "htmlName": "failed",
    "count": 0,
    "percentage": 0
},
    "meanNumberOfRequestsPerSecond": {
        "total": 0.4117647058823529,
        "ok": 0.4117647058823529,
        "ko": 0
    }
}
    },"req_edit-user-reque--361315984": {
        "type": "REQUEST",
        "name": "Edit user request",
"path": "Edit user request",
"pathFormatted": "req_edit-user-reque--361315984",
"stats": {
    "name": "Edit user request",
    "numberOfRequests": {
        "total": 2,
        "ok": 2,
        "ko": 0
    },
    "minResponseTime": {
        "total": 49,
        "ok": 49,
        "ko": 0
    },
    "maxResponseTime": {
        "total": 50,
        "ok": 50,
        "ko": 0
    },
    "meanResponseTime": {
        "total": 50,
        "ok": 50,
        "ko": 0
    },
    "standardDeviation": {
        "total": 1,
        "ok": 1,
        "ko": 0
    },
    "percentiles1": {
        "total": 50,
        "ok": 50,
        "ko": 0
    },
    "percentiles2": {
        "total": 50,
        "ok": 50,
        "ko": 0
    },
    "percentiles3": {
        "total": 50,
        "ok": 50,
        "ko": 0
    },
    "percentiles4": {
        "total": 50,
        "ok": 50,
        "ko": 0
    },
    "group1": {
    "name": "t < 800 ms",
    "htmlName": "t < 800 ms",
    "count": 2,
    "percentage": 100
},
    "group2": {
    "name": "800 ms <= t < 1200 ms",
    "htmlName": "t >= 800 ms <br> t < 1200 ms",
    "count": 0,
    "percentage": 0
},
    "group3": {
    "name": "t >= 1200 ms",
    "htmlName": "t >= 1200 ms",
    "count": 0,
    "percentage": 0
},
    "group4": {
    "name": "failed",
    "htmlName": "failed",
    "count": 0,
    "percentage": 0
},
    "meanNumberOfRequestsPerSecond": {
        "total": 0.11764705882352941,
        "ok": 0.11764705882352941,
        "ko": 0
    }
}
    }
}

}